smtpconnectx.py
smtpconnectx-0.1.dist-info/METADATA
smtpconnectx-0.1.dist-info/WHEEL
smtpconnectx-0.1.dist-info/top_level.txt
smtpconnectx-0.1.dist-info/RECORD
