Metadata-Version: 2.1
Name: smtpconnectx
Version: 0.1
Requires-Dist: requests
